a_pandas_ex_horizontal_explode/LICENSE
a_pandas_ex_horizontal_explode/README.MD
a_pandas_ex_horizontal_explode/__init__.py
a_pandas_ex_horizontal_explode/requirements.txt
a_pandas_ex_horizontal_explode/thirdparty.json
a_pandas_ex_horizontal_explode-0.10.dist-info/LICENSE.rst
a_pandas_ex_horizontal_explode-0.10.dist-info/METADATA
a_pandas_ex_horizontal_explode-0.10.dist-info/WHEEL
a_pandas_ex_horizontal_explode-0.10.dist-info/top_level.txt
a_pandas_ex_horizontal_explode-0.10.dist-info/RECORD
