Metadata-Version: 2.1
Name: a_pandas_ex_horizontal_explode
Version: 0.10
Summary: Explode list/tuples in columns
Home-page: https://github.com/hansalemaos/a_pandas_ex_horizontal_explode
Author: Johannes Fischer
Author-email: <aulasparticularesdealemaosp@gmail.com>
License: MIT
Keywords: Explode,pandas,DataFrame,Series
Classifier: Development Status :: 4 - Beta
Classifier: Programming Language :: Python :: 3 :: Only
Classifier: Programming Language :: Python :: 3.9
Classifier: Topic :: Scientific/Engineering :: Visualization
Classifier: Topic :: Software Development :: Libraries :: Python Modules
Classifier: Topic :: Text Editors :: Text Processing
Classifier: Topic :: Text Processing :: General
Classifier: Topic :: Text Processing :: Indexing
Classifier: Topic :: Text Processing :: Filters
Classifier: Topic :: Utilities
License-File: LICENSE.rst
